README.md
setup.cfg
setup.py
vizstack/__init__.py
vizstack/fragment_assembler.py
vizstack/lang.py
vizstack/schema.py
vizstack/view_assembler.py
vizstack/assemblers/__init__.py
vizstack/assemblers/dag.py
vizstack/assemblers/flow.py
vizstack/assemblers/grid.py
vizstack/assemblers/icon.py
vizstack/assemblers/image.py
vizstack/assemblers/keyvalue.py
vizstack/assemblers/sequence.py
vizstack/assemblers/switch.py
vizstack/assemblers/text.py
vizstack/assemblers/token.py
vizstack_py.egg-info/PKG-INFO
vizstack_py.egg-info/SOURCES.txt
vizstack_py.egg-info/dependency_links.txt
vizstack_py.egg-info/not-zip-safe
vizstack_py.egg-info/requires.txt
vizstack_py.egg-info/top_level.txt