Metadata-Version: 2.1
Name: vizstack-py
Version: 0.1.4
Summary: Generate Vizstack visualizations of Python programs.
Home-page: https://github.com/vizstack/vizstack
Author: Ryan Holmdahl & Nikhil Bhattasali
Author-email: vizstack@gmail.com
License: MIT
Platform: UNKNOWN
